{
	"class" : {
		"op:" : "btmanh 5/18/2012 12:36:43.572" },
	"instance" : {
		"=" : "SergeStinckwich 11/28/2012 15:55",
		"evaluateWithModel:" : "SergeStinckwich 11/28/2012 15:55",
		"expression" : "SergeStinckwich 11/28/2012 15:52",
		"expression:" : "SergeStinckwich 11/28/2012 15:52",
		"generateEvents" : "SergeStinckwich 11/28/2012 15:55",
		"isUnaryExpression" : "SergeStinckwich 11/28/2012 15:54",
		"negated" : "SergeStinckwich 11/28/2012 15:52",
		"normalize" : "SergeStinckwich 11/28/2012 15:53",
		"op" : "btmanh 5/18/2012 12:36:43.572",
		"op:" : "btmanh 5/18/2012 12:36:43.572",
		"printOn:" : "SergeStinckwich 11/28/2012 15:53",
		"sign" : "SergeStinckwich 11/28/2012 15:53" } }
